emu_sv/__init__.py
emu_sv/custom_callback_implementations.py
emu_sv/dense_operator.py
emu_sv/density_matrix_state.py
emu_sv/hamiltonian.py
emu_sv/lindblad_operator.py
emu_sv/sparse_operator.py
emu_sv/state_vector.py
emu_sv/sv_backend.py
emu_sv/sv_backend_impl.py
emu_sv/sv_config.py
emu_sv/time_evolution.py
emu_sv/utils.py
emu_sv-2.6.0.dist-info/METADATA
emu_sv-2.6.0.dist-info/WHEEL
emu_sv-2.6.0.dist-info/RECORD
