Metadata-Version: 2.4
Name: emu-sv
Version: 2.6.0
Summary: Pasqal State Vector based pulse emulator built on PyTorch
Project-URL: Documentation, https://pasqal-io.github.io/emulators/
Project-URL: Repository, https://github.com/pasqal-io/emulators
Project-URL: Issues, https://github.com/pasqal-io/emulators/issues
Author-email: Kemal Bidzhiev <kemal.bidzhiev@pasqal.com>, Stefano Grava <stefano.grava@pasqal.com>, Pablo Le Henaff <pablo.le-henaff@pasqal.com>, Mauro Mendizabal <mauro.mendizabal-pico@pasqal.com>, Elie Merhej <elie.merhej@pasqal.com>, Anton Quelle <anton.quelle@pasqal.com>
License: PASQAL OPEN-SOURCE SOFTWARE LICENSE AGREEMENT (MIT-derived)
Classifier: Programming Language :: Python :: 3.10
Classifier: Programming Language :: Python :: Implementation :: CPython
Classifier: Programming Language :: Python :: Implementation :: PyPy
Requires-Python: >=3.10
Requires-Dist: emu-base==2.6.0
